{
  "SPDXID": "SPDXRef-DOCUMENT",
  "spdxVersion": "SPDX-2.3",
  "creationInfo": {
    "comment": "This document has been automatically generated.",
    "creators": [
      "Tool: sbomconvert-0.1.0"
    ],
    "created": "2025-10-22T09:13:54Z",
    "licenseListVersion": "3.26"
  },
  "name": "nppftp-v0.30.22",
  "dataLicense": "CC0-1.0",
  "documentNamespace": "http://spdx.org/spdxdocs/nppftp-v0.30.22-dfbe4781-4406-4acd-9437-ffb16bbcc3ac",
  "packages": [
    {
      "SPDXID": "SPDXRef-Package-nppftp",
      "name": "nppftp",
      "versionInfo": "v0.30.22",
      "packageVersion": "v0.30.22",
      "primaryPackagePurpose": "LIBRARY",
      "downloadLocation": "https://github.com/ashkulz/NppFTP/releases/tag/v0.30.22",
      "filesAnalyzed": false,
      "homepage": "https://ashkulz.github.io/NppFTP/",
      "licenseConcluded": "NOASSERTION",
      "licenseDeclared": "NOASSERTION",
      "copyrightText": "Copyright 2010-2025.",
      "summary": "Plugin for Notepad++ allowing FTP, FTPS, FTPES and SFTP communications",
      "supplier" : "Person: Ashish Kulkarni"
    },
    {
      "SPDXID": "SPDXRef-Package-openssl",
      "name": "openssl",
      "versionInfo": "3.5.4",
      "packageVersion": "3.5.4",
      "primaryPackagePurpose": "LIBRARY",
      "downloadLocation": "https://github.com/openssl/openssl/releases/download/openssl-3.5.4/openssl-3.5.4.tar.gz",
      "filesAnalyzed": false,
      "packageFileName": "./libs/openssl",
      "homepage": "https://openssl-library.org/",
      "licenseConcluded": "NOASSERTION",
      "licenseDeclared": "Apache-2.0",
      "copyrightText": "copyright 1998-2025 The OpenSSL Project Authors. All Rights Reserved.",
      "description": "OpenSSL is a robust, commercial-grade, full-featured Open Source Toolkit for the Transport Layer Security (TLS) protocol formerly known as the Secure Sockets Layer (SSL) protocol. The protocol implementation is based on a full-strength general purpose cryptographic library, which can also be used stand-alone.",
      "supplier" : "Organization: OpenSSL Software Foundation (foundation@openssl.org)"
    },
    {
      "SPDXID": "SPDXRef-Package-libssh",
      "name": "libssh",
      "versionInfo": "0.11.4",
      "packageVersion": "0.11.4",
      "primaryPackagePurpose": "LIBRARY",
      "downloadLocation": "https://www.libssh.org/files/0.11/libssh-0.11.4.tar.xz",
      "filesAnalyzed": false,
      "packageFileName": "./libs/libssh",
      "homepage": "https://www.libssh.org/",
      "licenseConcluded": "NOASSERTION",
      "licenseDeclared": "NOASSERTION",
      "copyrightText": "copyright 2025 libssh – All rights reserved.",
      "description": "libssh is a multiplatform C library implementing the SSHv2 protocol on client and server side. With libssh, you can remotely execute programs, transfer files, use a secure and transparent tunnel, manage public keys and much more ...",
      "supplier" : "Person: Aris Adamantiadis"
    },
    {
      "SPDXID": "SPDXRef-Package-zlib",
      "name": "zlib",
      "versionInfo": "v1.3.1",
      "packageVersion": "v1.3.1",
      "primaryPackagePurpose": "LIBRARY",
      "downloadLocation": "https://github.com/madler/zlib/releases/download/v1.3.1/zlib-1.3.1.tar.gz",
      "filesAnalyzed": false,
      "packageFileName": "./libs/zlib",
      "homepage": "https://zlib.net/",
      "licenseConcluded": "NOASSERTION",
      "licenseDeclared": "NOASSERTION",
      "copyrightText": "zlib software copyright © 1995-2025 Jean-loup Gailly and Mark Adler.",
      "description": "A massively spiffy yet delicately unobtrusive compression library.",
      "supplier" : "Person: Mark Adler"
    }
  ],
  "relationships": [
    {
      "relatedSpdxElement": "SPDXRef-Package-nppftp",
      "relationshipType": "DESCRIBES",
      "spdxElementId": "SPDXRef-DOCUMENT"
    },
    {
      "spdxElementId": "SPDXRef-Package-nppftp",
      "relatedSpdxElement": "SPDXRef-Package-openssl",
      "relationshipType": "CONTAINS"
    },
    {
      "spdxElementId": "SPDXRef-Package-nppftp",
      "relatedSpdxElement": "SPDXRef-Package-libssh",
      "relationshipType": "CONTAINS"
    },
    {
      "spdxElementId": "SPDXRef-Package-nppftp",
      "relatedSpdxElement": "SPDXRef-Package-zlib",
      "relationshipType": "CONTAINS"
    }
  ]
}
